cyclic/__init__.py
cyclic/b.py
yclic_b-0.0.2.dist-info/LICENSE
yclic_b-0.0.2.dist-info/METADATA
yclic_b-0.0.2.dist-info/WHEEL
yclic_b-0.0.2.dist-info/top_level.txt
yclic_b-0.0.2.dist-info/RECORD
