Metadata-Version: 2.1
Name: yclic-b
Version: 0.0.2
Summary: A small package to test cyclic dependencies
Home-page: https://github.com/thibaultduponchelle/yclic-b
Author: Thibault Duponchelle
Author-email: thibault.duponchelle@gmail.com
License: UNKNOWN
Project-URL: Bug Tracker, https://github.com/thibaultduponchelle/yclic-b/issues
Platform: UNKNOWN
Classifier: Programming Language :: Python :: 3
Classifier: License :: OSI Approved :: MIT License
Classifier: Operating System :: OS Independent
Requires-Python: >=3.6
License-File: LICENSE
Requires-Dist: cyclic-a (>=0)
